[
  {
    "id": "claim-legacy-achievement-summary",
    "importance": "core",
    "text": {
      "zh": "Lasso 回归 是当前 legacy 展示中的一个 AI 历史节点。",
      "en": "Lasso is an AI history milestone in the current legacy presentation."
    },
    "sourceIds": [
      "source-regression-shrinkage-and-selection-via-the-lasso",
      "source-scikit-learn-lasso"
    ],
    "status": "needs-source"
  },
  {
    "id": "claim-legacy-description",
    "importance": "context",
    "text": {
      "zh": "<p>Lasso 为统计学家和机器学习实践者提供了一种构建稀疏线性模型的清晰方法。通过惩罚系数绝对值，它既正则化预测，又完成变量选择。其思想后来出现在稀疏建模、高维统计、压缩感知、生物信息学和可解释机器学习中。</p>",
      "en": "<p>The lasso gave statisticians and machine-learning practitioners a clean way to build sparse linear models. By penalizing the absolute size of coefficients, it both regularizes predictions and performs variable selection. Its ideas now appear in sparse modeling, high-dimensional statistics, compressed sensing, bioinformatics, and interpretable ML.</p>"
    },
    "sourceIds": [
      "source-regression-shrinkage-and-selection-via-the-lasso",
      "source-scikit-learn-lasso"
    ],
    "status": "needs-source"
  }
]
