[
  {
    "id": "source-image-to-image-translation-with-conditional-adversarial-networks",
    "type": "paper",
    "label": {
      "zh": "论文",
      "en": "Paper"
    },
    "title": {
      "zh": "《使用条件对抗网络进行图像到图像转换》",
      "en": "Image-to-Image Translation with Conditional Adversarial Networks"
    },
    "url": "https://arxiv.org/abs/1611.07004",
    "language": "en",
    "reliability": "primary",
    "notes": {
      "zh": "由 legacy generated milestone 的 achievement sources 迁移。",
      "en": "Migrated from generated legacy milestone achievement sources."
    },
    "purpose": "core-evidence"
  },
  {
    "id": "source-cvpr-open-access-paper-page",
    "type": "paper-page",
    "label": {
      "zh": "会议论文页面",
      "en": "Conference paper page"
    },
    "title": {
      "zh": "CVPR 开放论文页面",
      "en": "CVPR open-access paper page"
    },
    "url": "https://openaccess.thecvf.com/content_cvpr_2017/html/Isola_Image-To-Image_Translation_With_CVPR_2017_paper.html",
    "language": "en",
    "reliability": "secondary",
    "notes": {
      "zh": "由 legacy generated milestone 的 achievement sources 迁移。",
      "en": "Migrated from generated legacy milestone achievement sources."
    },
    "purpose": "alternate-access"
  },
  {
    "id": "source-pix2pix-project-page",
    "type": "project-page",
    "label": {
      "zh": "项目页面",
      "en": "Project page"
    },
    "title": {
      "zh": "Pix2Pix 项目页面",
      "en": "Pix2Pix project page"
    },
    "url": "https://phillipi.github.io/pix2pix/",
    "language": "en",
    "reliability": "secondary",
    "notes": {
      "zh": "由 legacy generated milestone 的 achievement sources 迁移。",
      "en": "Migrated from generated legacy milestone achievement sources."
    },
    "purpose": "background"
  }
]
